{
    "output": {
        "body": "<%=$0%>",
        "name": "<%= %>",
        "prefix": "out"
    },
    "for...Next": {
        "body": "For $1 To $2 ${3:Step}\n\t${4:' body}\nNext",
        "name": "For \u2026 in \u2026 Next",
        "prefix": "for"
    },
    "for...in": {
        "body": "For $1 in $2\n\t${3:' body}\nNext",
        "name": "For \u2026 in \u2026 Next",
        "prefix": "forin"
    },
    "if-else": {
        "body": "If ${1:condition} Then\n\t${2:' true}\nElse\n\t${3:' false}\nEnd if",
        "name": "If \u2026 End if",
        "prefix": "if"
    },
    "while": {
        "body": "While ${1:condition}\n\t${2:' body}\nLoop",
        "name": "While \u2026 Loop",
        "prefix": "while"
    },
    "do-while loop": {
        "body": "Do While ${1:condition}\n\t${2:' body}\nLoop",
        "name": "Do While \u2026 Loop",
        "prefix": "dowhile"
    },
    "do-until loop": {
        "body": "Do Until ${1:condition}\n\t${2:' body}\nLoop",
        "name": "Do Until \u2026 Loop",
        "prefix": "dountil"
    },
    "select case": {
        "body": "Select Case ${1:variable}\n\tCase ${2:condition}:\n\t\t${3:' Do Something}\nEnd Select",
        "name": "Select Case",
        "prefix": "sel"
    },
    "case": {
        "body": "Case ${2:condition}:\n\t${3:' Do Something}",
        "name": "Case",
        "prefix": "case"
    },
    "sub routine": {
        "body": "Sub ${1:name}\n\t${2:' Do Something...}\nEnd Sub",
        "name": "Sub Routine",
        "prefix": "sub"
    },
    "function": {
        "body": "${1|Public,Private|} Function ${2:name}\n\t${3:' Do Something...}\nEnd Function",
        "name": "Function",
        "prefix": "fun"
    },
    "include": {
        "body": "<!--#include ${1:file,virtual}=\"${2:filePath}\"-->",
        "name": "Include",
        "prefix": "inc"
    },
    "Request": {
        "body": "Request",
        "name": "Request",
        "prefix": "req"
    },
    "Request.Form": {
        "body": "Request.Form(\"${1:field}\")",
        "name": "Request.Form(\"\u2026\")",
        "prefix": "reqf"
    },
    "Request.QueryString": {
        "body": "Request.QueryString(\"${1:name}\")",
        "name": "Request.QueryString",
        "prefix": "qs"
    },
    "Response": {
        "body": "Response",
        "name": "Response",
        "prefix": "res"
    },
    "Request.Write": {
        "body": "Response.Write ",
        "name": "Response.Write",
        "prefix": "wr"
    },
    "Request.Redirect": {
        "body": "Response.Redirect(${1:to})",
        "name": "Response.Redirect",
        "prefix": "ri"
    },
    "Cookie Variables": {
        "body": "Response.Cookie(\"${1:whatever}\")",
        "name": "Cookie(\"\u2026\")",
        "prefix": "cook"
    },
    "Application Variables": {
        "body": "Application(\"$1\")",
        "name": "Application(\"\u2026\")",
        "prefix": "app"
    },
    "Session Variables": {
        "body": "Session(\"${1:whatever}\")",
        "name": "Session(\"\u2026\")",
        "prefix": "sess"
    },
    "Create Object": {
        "body": "Server.CreateObject(\"${1:whatever}\")",
        "name": "CreateObject\"\u2026\"",
        "prefix": "obj"
    },
    "Set Database Connection": {
        "body": "Set ${1:Db} = Server.CreateObject(\"ADODB.Connection\")\n${2:Conn} = \"${3:Connection_String}\"\n${1}.Open ${2}\n${4}\n${2}.Close\n${5}",
        "name": "Set DB Connection\"\u2026\"",
        "prefix": "dbcon"
    },
    "Set RecordSet": {
        "body": "Set ${1:Rs} = Server.CreateObject(\"ADODB.RecordSet\")\n${2:SQL} = \"${3:SQL_QUERY}\"\n${1}.Open ${2}, ${4:Db}\n${5}\n${1}.Close\n${6}",
        "name": "Set DB Connection\"\u2026\"",
        "prefix": "rs"
    },
    "Class": {
        "body": "Class ${1:ClassName}\n\n\t${2:' Add some properties or methods!}\n\nEnd Class\n${3}",
        "name": "Set Class",
        "prefix": "class"
    }
}